LICENSE
MANIFEST.in
README.rst
setup.py
shcmd/__init__.py
shcmd/cmd.py
shcmd/consts.py
shcmd/errors.py
shcmd/proc.py
shcmd/tailf.py
shcmd/tar.py
shcmd/utils.py
shcmd.egg-info/PKG-INFO
shcmd.egg-info/SOURCES.txt
shcmd.egg-info/dependency_links.txt
shcmd.egg-info/not-zip-safe
shcmd.egg-info/top_level.txt
tests/requirements.txt