Metadata-Version: 1.1
Name: shcmd
Version: 0.5.2
Summary: simple command-line wrapper
Home-page: https://github.com/skylothar/shcmd
Author: SkyLothar
Author-email: allothar@gmail.com
License: Apache 2.0
Platform: UNKNOWN
Classifier: Development Status :: 4 - Beta
Classifier: Intended Audience :: Developers
Classifier: Natural Language :: English
Classifier: License :: OSI Approved :: Apache Software License
Classifier: Programming Language :: Python
Classifier: Programming Language :: Python :: 3
Classifier: Programming Language :: Python :: 3.3
Classifier: Programming Language :: Python :: 3.4
